LICENSE.txt
MANIFEST.in
README.rst
packages
requirements.txt
setup.py
twoq/__init__.py
twoq/filtering.py
twoq/mapping.py
twoq/ordering.py
twoq/queuing.py
twoq/reducing.py
twoq/support.py
twoq.egg-info/PKG-INFO
twoq.egg-info/SOURCES.txt
twoq.egg-info/dependency_links.txt
twoq.egg-info/not-zip-safe
twoq.egg-info/requires.txt
twoq.egg-info/top_level.txt
twoq/active/__init__.py
twoq/active/filtering.py
twoq/active/mapping.py
twoq/active/mixins.py
twoq/active/ordering.py
twoq/active/queuing.py
twoq/active/reducing.py
twoq/lazy/__init__.py
twoq/lazy/filtering.py
twoq/lazy/mapping.py
twoq/lazy/mixins.py
twoq/lazy/ordering.py
twoq/lazy/queuing.py
twoq/lazy/reducing.py
twoq/tests/__init__.py
twoq/tests/active/__init__.py
twoq/tests/active/auto/__init__.py
twoq/tests/active/auto/test_autoq.py
twoq/tests/active/auto/test_filtering.py
twoq/tests/active/auto/test_mapping.py
twoq/tests/active/auto/test_ordering.py
twoq/tests/active/auto/test_reducing.py
twoq/tests/active/man/__init__.py
twoq/tests/active/man/test_filtering.py
twoq/tests/active/man/test_manq.py
twoq/tests/active/man/test_mapping.py
twoq/tests/active/man/test_ordering.py
twoq/tests/active/man/test_reducing.py
twoq/tests/auto/__init__.py
twoq/tests/auto/filtering.py
twoq/tests/auto/mapping.py
twoq/tests/auto/ordering.py
twoq/tests/auto/queuing.py
twoq/tests/auto/reducing.py
twoq/tests/lazy/__init__.py
twoq/tests/lazy/auto/__init__.py
twoq/tests/lazy/auto/test_autoq.py
twoq/tests/lazy/auto/test_filtering.py
twoq/tests/lazy/auto/test_mapping.py
twoq/tests/lazy/auto/test_ordering.py
twoq/tests/lazy/auto/test_reducing.py
twoq/tests/lazy/man/__init__.py
twoq/tests/lazy/man/test_filtering.py
twoq/tests/lazy/man/test_manq.py
twoq/tests/lazy/man/test_mapping.py
twoq/tests/lazy/man/test_ordering.py
twoq/tests/lazy/man/test_reducing.py
twoq/tests/man/__init__.py
twoq/tests/man/filtering.py
twoq/tests/man/manning.py
twoq/tests/man/mapping.py
twoq/tests/man/ordering.py
twoq/tests/man/queuing.py
twoq/tests/man/reducing.py