Metadata-Version: 1.0
Name: twoq
Version: 0.4.12
Summary: iterator chaining, underscored by a two-headed queue
Home-page: https://bitbucket.org/lcrees/twoq
Author: L. C. Rees
Author-email: lcrees@gmail.com
License: BSD
Keywords: queue generator utility iterator functional programming
Platform: UNKNOWN
Classifier: Development Status :: 3 - Alpha
Classifier: Intended Audience :: Developers
Classifier: License :: OSI Approved :: BSD License
Classifier: Natural Language :: English
Classifier: Operating System :: OS Independent
Classifier: Programming Language :: Python
Classifier: Programming Language :: Python :: 2
Classifier: Programming Language :: Python :: 3
Classifier: Programming Language :: Python :: 2.6
Classifier: Programming Language :: Python :: 2.7
Classifier: Programming Language :: Python :: 3.2
Classifier: Programming Language :: Python :: Implementation :: CPython
Classifier: Topic :: Software Development
Classifier: Topic :: Software Development :: Libraries
Classifier: Topic :: Utilities
